example_pkg_sckmkny/__init__.py
example_pkg_sckmkny/__main__.py
example_pkg_sckmkny/main.py
example_pkg_sckmkny/sub_pkg/__init__.py
example_pkg_sckmkny/sub_pkg/main.py
example_prj_sckmkny-0.3.0.dist-info/LICENSE
example_prj_sckmkny-0.3.0.dist-info/METADATA
example_prj_sckmkny-0.3.0.dist-info/WHEEL
example_prj_sckmkny-0.3.0.dist-info/top_level.txt
example_prj_sckmkny-0.3.0.dist-info/RECORD
