Metadata-Version: 2.1
Name: example-prj-sckmkny
Version: 0.3.0
Summary: A small example project with single package.
Home-page: https://github.com/larkintuckerllc/example-prj-sckmkny
Author: John Tucker
Author-email: john@larkintuckerllc.com
License: MIT
Platform: UNKNOWN
Classifier: Programming Language :: Python :: 3
Classifier: License :: OSI Approved :: MIT License
Classifier: Operating System :: OS Independent
Requires-Python: >=3.8
Requires-Dist: certifi (==2020.6.20)
Requires-Dist: chardet (==3.0.4)
Requires-Dist: idna (==2.10)
Requires-Dist: requests (==2.24.0)
Requires-Dist: urllib3 (==1.25.10)
